LICENSE
MANIFEST.in
README.rst
requirements-tests.txt
requirements.txt
setup.py
opbeatcli/__init__.py
opbeatcli/__main__.py
opbeatcli/cli.py
opbeatcli/client.py
opbeatcli/compat.py
opbeatcli/core.py
opbeatcli/exceptions.py
opbeatcli/log.py
opbeatcli/settings.py
opbeatcli.egg-info/PKG-INFO
opbeatcli.egg-info/SOURCES.txt
opbeatcli.egg-info/dependency_links.txt
opbeatcli.egg-info/entry_points.txt
opbeatcli.egg-info/not-zip-safe
opbeatcli.egg-info/requires.txt
opbeatcli.egg-info/top_level.txt
opbeatcli/commands/__init__.py
opbeatcli/commands/base.py
opbeatcli/commands/deployment.py
opbeatcli/deployment/__init__.py
opbeatcli/deployment/serialize.py
opbeatcli/deployment/vcs.py
opbeatcli/deployment/packages/__init__.py
opbeatcli/deployment/packages/base.py
opbeatcli/deployment/packages/component.py
opbeatcli/deployment/packages/deb.py
opbeatcli/deployment/packages/nodejs.py
opbeatcli/deployment/packages/other.py
opbeatcli/deployment/packages/python.py
opbeatcli/deployment/packages/rpm.py
opbeatcli/deployment/packages/ruby.py
opbeatcli/deployment/packages/types.py
opbeatcli/utils/__init__.py
opbeatcli/utils/ssh_config.py