Metadata-Version: 1.1
Name: opbeatcli
Version: 2.0.0
Summary: opbeatcli is a command line client for `Opbeat <https://opbeat.com/>`_.
Home-page: http://github.com/opbeat/opbeatcli
Author: Ron Cohen
Author-email: ron@opbeat.com
License: UNKNOWN
Platform: UNKNOWN
Classifier: Intended Audience :: Developers
Classifier: Intended Audience :: System Administrators
Classifier: Operating System :: OS Independent
Classifier: Topic :: Software Development
